README
setup.py
django_query_caching/__init__.py
django_query_caching/defaults.py
django_query_caching.egg-info/PKG-INFO
django_query_caching.egg-info/SOURCES.txt
django_query_caching.egg-info/dependency_links.txt
django_query_caching.egg-info/requires.txt
django_query_caching.egg-info/top_level.txt