Metadata-Version: 1.0
Name: django-query-caching
Version: 0.1.1
Summary: Caches the results of SQL queries transparently.
Home-page: https://github.com/SeanHayes/django-query-caching
Author: Seán Hayes
Author-email: sean@seanhayes.name
License: BSD
Keywords: django query cache
Platform: UNKNOWN
Classifier: Development Status :: 3 - Alpha
Classifier: Framework :: Django
Classifier: Intended Audience :: Developers
Classifier: License :: OSI Approved :: BSD License
Classifier: Operating System :: OS Independent
Classifier: Programming Language :: Python
Classifier: Programming Language :: Python :: 2.6
Classifier: Topic :: Database
Classifier: Topic :: Internet :: WWW/HTTP :: Dynamic Content
Classifier: Topic :: Software Development :: Libraries
Classifier: Topic :: Software Development :: Libraries :: Python Modules
